LICENSE
MANIFEST.in
README.md
setup.cfg
setup.py
gullveig/__init__.py
gullveig.egg-info/PKG-INFO
gullveig.egg-info/SOURCES.txt
gullveig.egg-info/dependency_links.txt
gullveig.egg-info/entry_points.txt
gullveig.egg-info/requires.txt
gullveig.egg-info/top_level.txt
gullveig/agent/__init__.py
gullveig/agent/agent.py
gullveig/agent/shmod.py
gullveig/agent/lib/__init__.py
gullveig/agent/lib/nativedp.py
gullveig/agent/lib/package.py
gullveig/agent/modules/__init__.py
gullveig/agent/modules/mod_apt.py
gullveig/agent/modules/mod_collectd.py
gullveig/agent/modules/mod_facter.py
gullveig/agent/modules/mod_fs.py
gullveig/agent/modules/mod_lwall.py
gullveig/agent/modules/mod_osquery.py
gullveig/agent/modules/mod_pkg.py
gullveig/agent/modules/mod_res.py
gullveig/agent/modules/mod_systemd.py
gullveig/common/__init__.py
gullveig/common/alerting.py
gullveig/common/configuration.py
gullveig/server/__init__.py
gullveig/server/analytics.py
gullveig/server/date.py
gullveig/server/dbi.py
gullveig/server/server.py
gullveig/server/dbal/__init__.py
gullveig/server/dbal/sqlite.py
gullveig/util/__init__.py
gullveig/util/util.py
gullveig/web/__init__.py
gullveig/web/api.py
gullveig/web/dbi.py
gullveig/web/kb.py
gullveig/web/web.py
gullveig/webui/dist/3rdpartylicenses.txt
gullveig/webui/dist/MaterialIcons-Regular.12a47ed5fd5585f0f422.woff2
gullveig/webui/dist/MaterialIcons-Regular.479700ea91d964d295d7.eot
gullveig/webui/dist/MaterialIcons-Regular.d4f2bf2eff4f11652ef1.ttf
gullveig/webui/dist/MaterialIcons-Regular.f2a0933406f783065152.woff
gullveig/webui/dist/favicon.ico
gullveig/webui/dist/index.html
gullveig/webui/dist/main.09d5411f88ab1571a833.js
gullveig/webui/dist/polyfills.654b0ce57de84441bf1a.js
gullveig/webui/dist/runtime.c51bd5b1c616d9ffddc1.js
gullveig/webui/dist/styles.f9bfd1c2566575e2fc40.css
gullveig/webui/dist/vendor.43b5674f18c492104aaa.js
gullveig/webui/dist/assets/favicon.svg
gullveig/webui/dist/assets/github.svg
gullveig/webui/dist/assets/logo.svg
gullveig/webui/dist/assets/no_data.svg