Metadata-Version: 2.1
Name: gullveig
Version: 0.1.26
Summary: Distributed systems and service monitoring
Home-page: https://github.com/Addvilz/gullveig
Author: Matiss Treinis
Author-email: matiss@hub256.com
License: Apache 2.0
Download-URL: https://github.com/Addvilz/gullveig
Platform: UNIX
Classifier: Development Status :: 4 - Beta
Classifier: Environment :: Console
Classifier: Intended Audience :: System Administrators
Classifier: License :: OSI Approved :: Apache Software License
Classifier: Operating System :: POSIX :: Linux
Classifier: Operating System :: POSIX
Classifier: Operating System :: Unix
Classifier: Programming Language :: Python :: 3 :: Only
Classifier: Topic :: System :: Monitoring
Classifier: Topic :: System :: Networking :: Monitoring
